subscriptionv1/__init__.py
subscriptionv1/client/__init__.py
subscriptionv1/client/subscription_api.py
subscriptionv1/client/subscription_client.py
subscriptionv1/middleware/__init__.py
subscriptionv1/middleware/middleware.py
yjsubscription-1.0.1.dist-info/METADATA
yjsubscription-1.0.1.dist-info/WHEEL
yjsubscription-1.0.1.dist-info/top_level.txt
yjsubscription-1.0.1.dist-info/RECORD
