Metadata-Version: 2.1
Name: yjsubscription
Version: 1.0.1
Summary: sdk in python for subscription
Home-page: https://console.cloud.baidu-int.com/devops/icode/repos/baidu/aivmp/subscription/tree/master
Author: haosixu
Author-email: haosixu@baidu.com
License: MIT
Classifier: Programming Language :: Python
Classifier: Programming Language :: Python :: 3
Classifier: Programming Language :: Python :: 3.7
Classifier: Programming Language :: Python :: 3.8
Classifier: Programming Language :: Python :: 3.9
Requires-Python: >=3.9
Requires-Dist: bce-python-sdk==0.8.87
Requires-Dist: bceidaas==0.0.1.dev2
Requires-Dist: bce-internal-sdk
Requires-Dist: pydantic
Requires-Dist: bceserver
Requires-Dist: bcelogger
Requires-Dist: fastapi
